starmadepy/starmade.py
starmadepy/__init__.py
starmadepy/binary.py
starmadepy/utils.py
starmadepy/data/items-complete.json
starmadepy-0.1.6.dist-info/METADATA
starmadepy-0.1.6.dist-info/WHEEL
starmadepy-0.1.6.dist-info/metadata.json
starmadepy-0.1.6.dist-info/pbr.json
starmadepy-0.1.6.dist-info/RECORD
starmadepy-0.1.6.dist-info/DESCRIPTION.rst
starmadepy-0.1.6.dist-info/top_level.txt
