Metadata-Version: 2.0
Name: starmadepy
Version: 0.1.6
Summary: An API for reading and manipulating Starmade game data
Home-page: https://github.com/DerekRies/starmadepy
Author: Derek Ries
Author-email: iamderekries@gmail.com
License: MIT
Keywords: starmade,game,data,template,blueprint
Platform: UNKNOWN
Classifier: Development Status :: 3 - Alpha
Classifier: Intended Audience :: Developers
Classifier: Topic :: Software Development :: Libraries
Classifier: License :: OSI Approved :: MIT License
Classifier: Programming Language :: Python :: 2.6
Classifier: Programming Language :: Python :: 2.7
